HISTORY
LICENSE
README
__init__.py
admin.py
localsettings.py.generic
manage.py
settings.py
setup.cfg
setup.py
urls.py
views.py
Docs/Makefile
Docs/make.bat
Docs/build/doctrees/environment.pickle
Docs/build/doctrees/index.doctree
Docs/build/html/.buildinfo
Docs/build/html/api.html
Docs/build/html/concepts.html
Docs/build/html/genindex.html
Docs/build/html/index.html
Docs/build/html/installation.html
Docs/build/html/objects.inv
Docs/build/html/py-modindex.html
Docs/build/html/search.html
Docs/build/html/searchindex.js
Docs/build/html/_modules/index.html
Docs/build/html/_modules/io.html
Docs/build/html/_modules/experimentdb/cloning/models.html
Docs/build/html/_modules/experimentdb/data/lookups.html
Docs/build/html/_modules/experimentdb/data/models.html
Docs/build/html/_modules/experimentdb/data/views.html
Docs/build/html/_modules/experimentdb/datasets/models.html
Docs/build/html/_modules/experimentdb/datasets/views.html
Docs/build/html/_modules/experimentdb/external/models.html
Docs/build/html/_modules/experimentdb/external/tests.html
Docs/build/html/_modules/experimentdb/proteins/lookups.html
Docs/build/html/_modules/experimentdb/proteins/models.html
Docs/build/html/_modules/experimentdb/proteins/urls.html
Docs/build/html/_modules/experimentdb/proteins/views.html
Docs/build/html/_modules/experimentdb/reagents/lookups.html
Docs/build/html/_modules/experimentdb/reagents/models.html
Docs/build/html/_modules/experimentdb/reagents/tests.html
Docs/build/html/_modules/experimentdb/reagents/views.html
Docs/build/html/_modules/experimentdb/sharing/models.html
Docs/build/html/_modules/experimentdb/sharing/tests.html
Docs/build/html/_modules/experimentdb/sharing/urls.html
Docs/build/html/_sources/index.txt
Docs/build/html/_static/basic.css
Docs/build/html/_static/default.css
Docs/build/html/_static/doctools.js
Docs/build/html/_static/file.png
Docs/build/html/_static/jquery.js
Docs/build/html/_static/minus.png
Docs/build/html/_static/plus.png
Docs/build/html/_static/pygments.css
experimentdb.egg-info/PKG-INFO
experimentdb.egg-info/SOURCES.txt
experimentdb.egg-info/dependency_links.txt
experimentdb.egg-info/entry_points.txt
experimentdb.egg-info/requires.txt
experimentdb.egg-info/top_level.txt
experimentdb.egg-info/zip-safe
