Metadata-Version: 1.0
Name: experimentdb
Version: 0.2
Summary: A web based application for storage and organization of data regarding experimental data.
Home-page: http://code.google.com/p/experimentdb/
Author: Dave Bridges
Author-email: dave.bridges@gmail.com
License: BSD
Keywords: experiment,LIMS,data,science,data-management
Platform: UNKNOWN
Classifier: Development Status :: 4 - Beta
Classifier: Framework :: Django
Classifier: Natural Language :: English
Classifier: Environment :: Web Environment
Classifier: Intended Audience :: Developers
Classifier: License :: OSI Approved :: BSD License
Classifier: Operating System :: OS Independent
Classifier: Programming Language :: Python
Classifier: Intended Audience :: Science/Research
Classifier: Topic :: Database :: Front-Ends
Classifier: Topic :: Scientific/Engineering :: Bio-Informatics
Classifier: Topic :: Internet :: WWW/HTTP
